setup.py
python_pyqt5_vstructui.egg-info/PKG-INFO
python_pyqt5_vstructui.egg-info/SOURCES.txt
python_pyqt5_vstructui.egg-info/dependency_links.txt
python_pyqt5_vstructui.egg-info/requires.txt
python_pyqt5_vstructui.egg-info/top_level.txt
vstructui/__init__.py
vstructui/common.py
vstructui/mutablenamedtuple.py
vstructui/tree.py
vstructui/vstruct_parser.py
vstructui/vstructui.py
vstructui/vstructui.ui
vstructui/defs/patchbits.py
vstructui/defs/primitives.py
vstructui/defs/sdb.py
vstructui/defs/windows.py